greetsub/__init__.py
greetsub/greetinner.py
greetsub-0.1.2.dist-info/METADATA
greetsub-0.1.2.dist-info/WHEEL
greetsub-0.1.2.dist-info/top_level.txt
greetsub-0.1.2.dist-info/RECORD
